{
	"country_code": "JP",
	"parent_id": "634",
	"locale": "ja-Latn",
	"address": {
		"6348586": {
			"postcode": "634-8586",
			"prefecture_name": "Nara-ken",
			"city_name": "Kashihara-shi",
			"ward_name": "",
			"town_name": "八木町",
			"building_name": "１丁目１−１８",
			"organization_name": "橿原市役所",
			"region_code": "関西",
			"prefecture_code": "奈良県",
			"city_code": "橿原市",
			"translations": {
				"ja": {
					"prefecture_name": "奈良県",
					"city_name": "橿原市",
					"ward_name": "",
					"town_name": "八木町",
					"building_name": "１丁目１−１８",
					"organization_name": "橿原市役所"
				}
			}
		},
		"6348585": {
			"postcode": "634-8585",
			"prefecture_name": "Nara-ken",
			"city_name": "Kashihara-shi",
			"ward_name": "",
			"town_name": "雲梯町",
			"building_name": "５９４",
			"organization_name": "三和澱粉工業　株式会社",
			"region_code": "関西",
			"prefecture_code": "奈良県",
			"city_code": "橿原市",
			"translations": {
				"ja": {
					"prefecture_name": "奈良県",
					"city_name": "橿原市",
					"ward_name": "",
					"town_name": "雲梯町",
					"building_name": "５９４",
					"organization_name": "三和澱粉工業　株式会社"
				}
			}
		},
		"6348580": {
			"postcode": "634-8580",
			"prefecture_name": "Nara-ken",
			"city_name": "Kashihara-shi",
			"ward_name": "",
			"town_name": "新堂町",
			"building_name": "３１３−１",
			"organization_name": "株式会社　タカトリ",
			"region_code": "関西",
			"prefecture_code": "奈良県",
			"city_code": "橿原市",
			"translations": {
				"ja": {
					"prefecture_name": "奈良県",
					"city_name": "橿原市",
					"ward_name": "",
					"town_name": "新堂町",
					"building_name": "３１３−１",
					"organization_name": "株式会社　タカトリ"
				}
			}
		},
		"6348567": {
			"postcode": "634-8567",
			"prefecture_name": "Nara-ken",
			"city_name": "Kashihara-shi",
			"ward_name": "",
			"town_name": "観音寺町",
			"building_name": "９−２",
			"organization_name": "佐藤薬品工業　株式会社",
			"region_code": "関西",
			"prefecture_code": "奈良県",
			"city_code": "橿原市",
			"translations": {
				"ja": {
					"prefecture_name": "奈良県",
					"city_name": "橿原市",
					"ward_name": "",
					"town_name": "観音寺町",
					"building_name": "９−２",
					"organization_name": "佐藤薬品工業　株式会社"
				}
			}
		},
		"6348561": {
			"postcode": "634-8561",
			"prefecture_name": "Nara-ken",
			"city_name": "Kashihara-shi",
			"ward_name": "",
			"town_name": "大久保町",
			"building_name": "３０２番１",
			"organization_name": "奈良県　市町村職員共済組合",
			"region_code": "関西",
			"prefecture_code": "奈良県",
			"city_code": "橿原市",
			"translations": {
				"ja": {
					"prefecture_name": "奈良県",
					"city_name": "橿原市",
					"ward_name": "",
					"town_name": "大久保町",
					"building_name": "３０２番１",
					"organization_name": "奈良県　市町村職員共済組合"
				}
			}
		},
		"6348560": {
			"postcode": "634-8560",
			"prefecture_name": "Nara-ken",
			"city_name": "Kashihara-shi",
			"ward_name": "",
			"town_name": "城殿町",
			"building_name": "４５９番地",
			"organization_name": "大和平野土地改良区事務所",
			"region_code": "関西",
			"prefecture_code": "奈良県",
			"city_code": "橿原市",
			"translations": {
				"ja": {
					"prefecture_name": "奈良県",
					"city_name": "橿原市",
					"ward_name": "",
					"town_name": "城殿町",
					"building_name": "４５９番地",
					"organization_name": "大和平野土地改良区事務所"
				}
			}
		},
		"6348555": {
			"postcode": "634-8555",
			"prefecture_name": "Nara-ken",
			"city_name": "Kashihara-shi",
			"ward_name": "",
			"town_name": "十市町",
			"building_name": "３３３番地２号",
			"organization_name": "株式会社　ジェイテクト　奈良工場",
			"region_code": "関西",
			"prefecture_code": "奈良県",
			"city_code": "橿原市",
			"translations": {
				"ja": {
					"prefecture_name": "奈良県",
					"city_name": "橿原市",
					"ward_name": "",
					"town_name": "十市町",
					"building_name": "３３３番地２号",
					"organization_name": "株式会社　ジェイテクト　奈良工場"
				}
			}
		},
		"6348551": {
			"postcode": "634-8551",
			"prefecture_name": "Nara-ken",
			"city_name": "Kashihara-shi",
			"ward_name": "",
			"town_name": "曽我町",
			"building_name": "８００",
			"organization_name": "株式会社　タカギ",
			"region_code": "関西",
			"prefecture_code": "奈良県",
			"city_code": "橿原市",
			"translations": {
				"ja": {
					"prefecture_name": "奈良県",
					"city_name": "橿原市",
					"ward_name": "",
					"town_name": "曽我町",
					"building_name": "８００",
					"organization_name": "株式会社　タカギ"
				}
			}
		},
		"6348550": {
			"postcode": "634-8550",
			"prefecture_name": "Nara-ken",
			"city_name": "Kashihara-shi",
			"ward_name": "",
			"town_name": "久米町",
			"building_name": "９３４",
			"organization_name": "橿原神宮",
			"region_code": "関西",
			"prefecture_code": "奈良県",
			"city_code": "橿原市",
			"translations": {
				"ja": {
					"prefecture_name": "奈良県",
					"city_name": "橿原市",
					"ward_name": "",
					"town_name": "久米町",
					"building_name": "９３４",
					"organization_name": "橿原神宮"
				}
			}
		},
		"6348524": {
			"postcode": "634-8524",
			"prefecture_name": "Nara-ken",
			"city_name": "Kashihara-shi",
			"ward_name": "",
			"town_name": "四条町",
			"building_name": "８４０",
			"organization_name": "奈良県立医科大学　看護短期大学部",
			"region_code": "関西",
			"prefecture_code": "奈良県",
			"city_code": "橿原市",
			"translations": {
				"ja": {
					"prefecture_name": "奈良県",
					"city_name": "橿原市",
					"ward_name": "",
					"town_name": "四条町",
					"building_name": "８４０",
					"organization_name": "奈良県立医科大学　看護短期大学部"
				}
			}
		},
		"6348523": {
			"postcode": "634-8523",
			"prefecture_name": "Nara-ken",
			"city_name": "Kashihara-shi",
			"ward_name": "",
			"town_name": "四条町",
			"building_name": "８４０",
			"organization_name": "奈良県立医科大学付属図書館",
			"region_code": "関西",
			"prefecture_code": "奈良県",
			"city_code": "橿原市",
			"translations": {
				"ja": {
					"prefecture_name": "奈良県",
					"city_name": "橿原市",
					"ward_name": "",
					"town_name": "四条町",
					"building_name": "８４０",
					"organization_name": "奈良県立医科大学付属図書館"
				}
			}
		},
		"6348522": {
			"postcode": "634-8522",
			"prefecture_name": "Nara-ken",
			"city_name": "Kashihara-shi",
			"ward_name": "",
			"town_name": "四条町",
			"building_name": "８４０",
			"organization_name": "奈良県立医科大学付属病院",
			"region_code": "関西",
			"prefecture_code": "奈良県",
			"city_code": "橿原市",
			"translations": {
				"ja": {
					"prefecture_name": "奈良県",
					"city_name": "橿原市",
					"ward_name": "",
					"town_name": "四条町",
					"building_name": "８４０",
					"organization_name": "奈良県立医科大学付属病院"
				}
			}
		},
		"6348521": {
			"postcode": "634-8521",
			"prefecture_name": "Nara-ken",
			"city_name": "Kashihara-shi",
			"ward_name": "",
			"town_name": "四条町",
			"building_name": "８４０",
			"organization_name": "奈良県立医科大学",
			"region_code": "関西",
			"prefecture_code": "奈良県",
			"city_code": "橿原市",
			"translations": {
				"ja": {
					"prefecture_name": "奈良県",
					"city_name": "橿原市",
					"ward_name": "",
					"town_name": "四条町",
					"building_name": "８４０",
					"organization_name": "奈良県立医科大学"
				}
			}
		},
		"6348511": {
			"postcode": "634-8511",
			"prefecture_name": "Nara-ken",
			"city_name": "Kashihara-shi",
			"ward_name": "",
			"town_name": "北八木町",
			"building_name": "３丁目６５−１１",
			"organization_name": "株式会社　近鉄百貨店　橿原店",
			"region_code": "関西",
			"prefecture_code": "奈良県",
			"city_code": "橿原市",
			"translations": {
				"ja": {
					"prefecture_name": "奈良県",
					"city_name": "橿原市",
					"ward_name": "",
					"town_name": "北八木町",
					"building_name": "３丁目６５−１１",
					"organization_name": "株式会社　近鉄百貨店　橿原店"
				}
			}
		},
		"6348510": {
			"postcode": "634-8510",
			"prefecture_name": "Nara-ken",
			"city_name": "Kashihara-shi",
			"ward_name": "",
			"town_name": "中曽司町",
			"building_name": "５５５−１",
			"organization_name": "オカハシ　株式会社",
			"region_code": "関西",
			"prefecture_code": "奈良県",
			"city_code": "橿原市",
			"translations": {
				"ja": {
					"prefecture_name": "奈良県",
					"city_name": "橿原市",
					"ward_name": "",
					"town_name": "中曽司町",
					"building_name": "５５５−１",
					"organization_name": "オカハシ　株式会社"
				}
			}
		},
		"6348507": {
			"postcode": "634-8507",
			"prefecture_name": "Nara-ken",
			"city_name": "Kashihara-shi",
			"ward_name": "",
			"town_name": "常盤町",
			"building_name": "６０５番地の５",
			"organization_name": "奈良県中和保健所",
			"region_code": "関西",
			"prefecture_code": "奈良県",
			"city_code": "橿原市",
			"translations": {
				"ja": {
					"prefecture_name": "奈良県",
					"city_name": "橿原市",
					"ward_name": "",
					"town_name": "常盤町",
					"building_name": "６０５番地の５",
					"organization_name": "奈良県中和保健所"
				}
			}
		},
		"6348506": {
			"postcode": "634-8506",
			"prefecture_name": "Nara-ken",
			"city_name": "Kashihara-shi",
			"ward_name": "",
			"town_name": "常盤町",
			"building_name": "６０５番地の５",
			"organization_name": "中南和県税事務所",
			"region_code": "関西",
			"prefecture_code": "奈良県",
			"city_code": "橿原市",
			"translations": {
				"ja": {
					"prefecture_name": "奈良県",
					"city_name": "橿原市",
					"ward_name": "",
					"town_name": "常盤町",
					"building_name": "６０５番地の５",
					"organization_name": "中南和県税事務所"
				}
			}
		},
		"6348505": {
			"postcode": "634-8505",
			"prefecture_name": "Nara-ken",
			"city_name": "Kashihara-shi",
			"ward_name": "",
			"town_name": "醍醐町",
			"building_name": "１２２−１",
			"organization_name": "マルコ　株式会社　本社事務所",
			"region_code": "関西",
			"prefecture_code": "奈良県",
			"city_code": "橿原市",
			"translations": {
				"ja": {
					"prefecture_name": "奈良県",
					"city_name": "橿原市",
					"ward_name": "",
					"town_name": "醍醐町",
					"building_name": "１２２−１",
					"organization_name": "マルコ　株式会社　本社事務所"
				}
			}
		},
		"6348503": {
			"postcode": "634-8503",
			"prefecture_name": "Nara-ken",
			"city_name": "Kashihara-shi",
			"ward_name": "",
			"town_name": "四条町",
			"building_name": "６１８−１",
			"organization_name": "奈良県　警察交通反則通告センター",
			"region_code": "関西",
			"prefecture_code": "奈良県",
			"city_code": "橿原市",
			"translations": {
				"ja": {
					"prefecture_name": "奈良県",
					"city_name": "橿原市",
					"ward_name": "",
					"town_name": "四条町",
					"building_name": "６１８−１",
					"organization_name": "奈良県　警察交通反則通告センター"
				}
			}
		},
		"6348502": {
			"postcode": "634-8502",
			"prefecture_name": "Nara-ken",
			"city_name": "Kashihara-shi",
			"ward_name": "",
			"town_name": "内膳町",
			"building_name": "５丁目５−８",
			"organization_name": "奈良県医師会",
			"region_code": "関西",
			"prefecture_code": "奈良県",
			"city_code": "橿原市",
			"translations": {
				"ja": {
					"prefecture_name": "奈良県",
					"city_name": "橿原市",
					"ward_name": "",
					"town_name": "内膳町",
					"building_name": "５丁目５−８",
					"organization_name": "奈良県医師会"
				}
			}
		},
		"6348501": {
			"postcode": "634-8501",
			"prefecture_name": "Nara-ken",
			"city_name": "Kashihara-shi",
			"ward_name": "",
			"town_name": "四条町",
			"building_name": "６１８−１",
			"organization_name": "橿原警察署",
			"region_code": "関西",
			"prefecture_code": "奈良県",
			"city_code": "橿原市",
			"translations": {
				"ja": {
					"prefecture_name": "奈良県",
					"city_name": "橿原市",
					"ward_name": "",
					"town_name": "四条町",
					"building_name": "６１８−１",
					"organization_name": "橿原警察署"
				}
			}
		},
		"6340847": {
			"postcode": "634-0847",
			"prefecture_name": "Nara-ken",
			"city_name": "Kashihara-shi",
			"ward_name": "",
			"town_name": "Hidakacho",
			"building_name": "",
			"organization_name": "",
			"translations": {
				"ja": {
					"prefecture_name": "奈良県",
					"city_name": "橿原市",
					"ward_name": "",
					"town_name": "飯高町",
					"building_name": "",
					"organization_name": ""
				}
			},
			"region_code": "関西",
			"prefecture_code": "奈良県",
			"city_code": "橿原市"
		},
		"6340846": {
			"postcode": "634-0846",
			"prefecture_name": "Nara-ken",
			"city_name": "Kashihara-shi",
			"ward_name": "",
			"town_name": "Ozukucho",
			"building_name": "",
			"organization_name": "",
			"translations": {
				"ja": {
					"prefecture_name": "奈良県",
					"city_name": "橿原市",
					"ward_name": "",
					"town_name": "小槻町",
					"building_name": "",
					"organization_name": ""
				}
			},
			"region_code": "関西",
			"prefecture_code": "奈良県",
			"city_code": "橿原市"
		},
		"6340845": {
			"postcode": "634-0845",
			"prefecture_name": "Nara-ken",
			"city_name": "Kashihara-shi",
			"ward_name": "",
			"town_name": "Nakazoshicho",
			"building_name": "",
			"organization_name": "",
			"translations": {
				"ja": {
					"prefecture_name": "奈良県",
					"city_name": "橿原市",
					"ward_name": "",
					"town_name": "中曽司町",
					"building_name": "",
					"organization_name": ""
				}
			},
			"region_code": "関西",
			"prefecture_code": "奈良県",
			"city_code": "橿原市"
		},
		"6340844": {
			"postcode": "634-0844",
			"prefecture_name": "Nara-ken",
			"city_name": "Kashihara-shi",
			"ward_name": "",
			"town_name": "Tsuchihashicho",
			"building_name": "",
			"organization_name": "",
			"translations": {
				"ja": {
					"prefecture_name": "奈良県",
					"city_name": "橿原市",
					"ward_name": "",
					"town_name": "土橋町",
					"building_name": "",
					"organization_name": ""
				}
			},
			"region_code": "関西",
			"prefecture_code": "奈良県",
			"city_code": "橿原市"
		},
		"6340843": {
			"postcode": "634-0843",
			"prefecture_name": "Nara-ken",
			"city_name": "Kashihara-shi",
			"ward_name": "",
			"town_name": "Kitamyohojicho",
			"building_name": "",
			"organization_name": "",
			"translations": {
				"ja": {
					"prefecture_name": "奈良県",
					"city_name": "橿原市",
					"ward_name": "",
					"town_name": "北妙法寺町",
					"building_name": "",
					"organization_name": ""
				}
			},
			"region_code": "関西",
			"prefecture_code": "奈良県",
			"city_code": "橿原市"
		},
		"6340842": {
			"postcode": "634-0842",
			"prefecture_name": "Nara-ken",
			"city_name": "Kashihara-shi",
			"ward_name": "",
			"town_name": "Toyodacho",
			"building_name": "",
			"organization_name": "",
			"translations": {
				"ja": {
					"prefecture_name": "奈良県",
					"city_name": "橿原市",
					"ward_name": "",
					"town_name": "豊田町",
					"building_name": "",
					"organization_name": ""
				}
			},
			"region_code": "関西",
			"prefecture_code": "奈良県",
			"city_code": "橿原市"
		},
		"6340841": {
			"postcode": "634-0841",
			"prefecture_name": "Nara-ken",
			"city_name": "Kashihara-shi",
			"ward_name": "",
			"town_name": "Ogakicho",
			"building_name": "",
			"organization_name": "",
			"translations": {
				"ja": {
					"prefecture_name": "奈良県",
					"city_name": "橿原市",
					"ward_name": "",
					"town_name": "大垣町",
					"building_name": "",
					"organization_name": ""
				}
			},
			"region_code": "関西",
			"prefecture_code": "奈良県",
			"city_code": "橿原市"
		},
		"6340837": {
			"postcode": "634-0837",
			"prefecture_name": "Nara-ken",
			"city_name": "Kashihara-shi",
			"ward_name": "",
			"town_name": "Magarikawacho",
			"building_name": "",
			"organization_name": "",
			"translations": {
				"ja": {
					"prefecture_name": "奈良県",
					"city_name": "橿原市",
					"ward_name": "",
					"town_name": "曲川町",
					"building_name": "",
					"organization_name": ""
				}
			},
			"region_code": "関西",
			"prefecture_code": "奈良県",
			"city_code": "橿原市"
		},
		"6340836": {
			"postcode": "634-0836",
			"prefecture_name": "Nara-ken",
			"city_name": "Kashihara-shi",
			"ward_name": "",
			"town_name": "Shindocho",
			"building_name": "",
			"organization_name": "",
			"translations": {
				"ja": {
					"prefecture_name": "奈良県",
					"city_name": "橿原市",
					"ward_name": "",
					"town_name": "新堂町",
					"building_name": "",
					"organization_name": ""
				}
			},
			"region_code": "関西",
			"prefecture_code": "奈良県",
			"city_code": "橿原市"
		},
		"6340835": {
			"postcode": "634-0835",
			"prefecture_name": "Nara-ken",
			"city_name": "Kashihara-shi",
			"ward_name": "",
			"town_name": "Higashibojocho",
			"building_name": "",
			"organization_name": "",
			"translations": {
				"ja": {
					"prefecture_name": "奈良県",
					"city_name": "橿原市",
					"ward_name": "",
					"town_name": "東坊城町",
					"building_name": "",
					"organization_name": ""
				}
			},
			"region_code": "関西",
			"prefecture_code": "奈良県",
			"city_code": "橿原市"
		},
		"6340834": {
			"postcode": "634-0834",
			"prefecture_name": "Nara-ken",
			"city_name": "Kashihara-shi",
			"ward_name": "",
			"town_name": "Unatecho",
			"building_name": "",
			"organization_name": "",
			"translations": {
				"ja": {
					"prefecture_name": "奈良県",
					"city_name": "橿原市",
					"ward_name": "",
					"town_name": "雲梯町",
					"building_name": "",
					"organization_name": ""
				}
			},
			"region_code": "関西",
			"prefecture_code": "奈良県",
			"city_code": "橿原市"
		},
		"6340833": {
			"postcode": "634-0833",
			"prefecture_name": "Nara-ken",
			"city_name": "Kashihara-shi",
			"ward_name": "",
			"town_name": "Imbecho",
			"building_name": "",
			"organization_name": "",
			"translations": {
				"ja": {
					"prefecture_name": "奈良県",
					"city_name": "橿原市",
					"ward_name": "",
					"town_name": "忌部町",
					"building_name": "",
					"organization_name": ""
				}
			},
			"region_code": "関西",
			"prefecture_code": "奈良県",
			"city_code": "橿原市"
		},
		"6340832": {
			"postcode": "634-0832",
			"prefecture_name": "Nara-ken",
			"city_name": "Kashihara-shi",
			"ward_name": "",
			"town_name": "Goicho",
			"building_name": "",
			"organization_name": "",
			"translations": {
				"ja": {
					"prefecture_name": "奈良県",
					"city_name": "橿原市",
					"ward_name": "",
					"town_name": "五井町",
					"building_name": "",
					"organization_name": ""
				}
			},
			"region_code": "関西",
			"prefecture_code": "奈良県",
			"city_code": "橿原市"
		},
		"6340831": {
			"postcode": "634-0831",
			"prefecture_name": "Nara-ken",
			"city_name": "Kashihara-shi",
			"ward_name": "",
			"town_name": "Sogacho",
			"building_name": "",
			"organization_name": "",
			"translations": {
				"ja": {
					"prefecture_name": "奈良県",
					"city_name": "橿原市",
					"ward_name": "",
					"town_name": "曽我町",
					"building_name": "",
					"organization_name": ""
				}
			},
			"region_code": "関西",
			"prefecture_code": "奈良県",
			"city_code": "橿原市"
		},
		"6340829": {
			"postcode": "634-0829",
			"prefecture_name": "Nara-ken",
			"city_name": "Kashihara-shi",
			"ward_name": "",
			"town_name": "Yoshidacho",
			"building_name": "",
			"organization_name": "",
			"translations": {
				"ja": {
					"prefecture_name": "奈良県",
					"city_name": "橿原市",
					"ward_name": "",
					"town_name": "吉田町",
					"building_name": "",
					"organization_name": ""
				}
			},
			"region_code": "関西",
			"prefecture_code": "奈良県",
			"city_code": "橿原市"
		},
		"6340828": {
			"postcode": "634-0828",
			"prefecture_name": "Nara-ken",
			"city_name": "Kashihara-shi",
			"ward_name": "",
			"town_name": "Furukawacho",
			"building_name": "",
			"organization_name": "",
			"translations": {
				"ja": {
					"prefecture_name": "奈良県",
					"city_name": "橿原市",
					"ward_name": "",
					"town_name": "古川町",
					"building_name": "",
					"organization_name": ""
				}
			},
			"region_code": "関西",
			"prefecture_code": "奈良県",
			"city_code": "橿原市"
		},
		"6340827": {
			"postcode": "634-0827",
			"prefecture_name": "Nara-ken",
			"city_name": "Kashihara-shi",
			"ward_name": "",
			"town_name": "Koyocho",
			"building_name": "",
			"organization_name": "",
			"translations": {
				"ja": {
					"prefecture_name": "奈良県",
					"city_name": "橿原市",
					"ward_name": "",
					"town_name": "光陽町",
					"building_name": "",
					"organization_name": ""
				}
			},
			"region_code": "関西",
			"prefecture_code": "奈良県",
			"city_code": "橿原市"
		},
		"6340826": {
			"postcode": "634-0826",
			"prefecture_name": "Nara-ken",
			"city_name": "Kashihara-shi",
			"ward_name": "",
			"town_name": "Kawanishicho",
			"building_name": "",
			"organization_name": "",
			"translations": {
				"ja": {
					"prefecture_name": "奈良県",
					"city_name": "橿原市",
					"ward_name": "",
					"town_name": "川西町",
					"building_name": "",
					"organization_name": ""
				}
			},
			"region_code": "関西",
			"prefecture_code": "奈良県",
			"city_code": "橿原市"
		},
		"6340825": {
			"postcode": "634-0825",
			"prefecture_name": "Nara-ken",
			"city_name": "Kashihara-shi",
			"ward_name": "",
			"town_name": "Kannonjicho",
			"building_name": "",
			"organization_name": "",
			"translations": {
				"ja": {
					"prefecture_name": "奈良県",
					"city_name": "橿原市",
					"ward_name": "",
					"town_name": "観音寺町",
					"building_name": "",
					"organization_name": ""
				}
			},
			"region_code": "関西",
			"prefecture_code": "奈良県",
			"city_code": "橿原市"
		},
		"6340824": {
			"postcode": "634-0824",
			"prefecture_name": "Nara-ken",
			"city_name": "Kashihara-shi",
			"ward_name": "",
			"town_name": "Kazucho",
			"building_name": "",
			"organization_name": "",
			"translations": {
				"ja": {
					"prefecture_name": "奈良県",
					"city_name": "橿原市",
					"ward_name": "",
					"town_name": "一町",
					"building_name": "",
					"organization_name": ""
				}
			},
			"region_code": "関西",
			"prefecture_code": "奈良県",
			"city_code": "橿原市"
		},
		"6340823": {
			"postcode": "634-0823",
			"prefecture_name": "Nara-ken",
			"city_name": "Kashihara-shi",
			"ward_name": "",
			"town_name": "Kitaochicho",
			"building_name": "",
			"organization_name": "",
			"translations": {
				"ja": {
					"prefecture_name": "奈良県",
					"city_name": "橿原市",
					"ward_name": "",
					"town_name": "北越智町",
					"building_name": "",
					"organization_name": ""
				}
			},
			"region_code": "関西",
			"prefecture_code": "奈良県",
			"city_code": "橿原市"
		},
		"6340822": {
			"postcode": "634-0822",
			"prefecture_name": "Nara-ken",
			"city_name": "Kashihara-shi",
			"ward_name": "",
			"town_name": "Toriyacho",
			"building_name": "",
			"organization_name": "",
			"translations": {
				"ja": {
					"prefecture_name": "奈良県",
					"city_name": "橿原市",
					"ward_name": "",
					"town_name": "鳥屋町",
					"building_name": "",
					"organization_name": ""
				}
			},
			"region_code": "関西",
			"prefecture_code": "奈良県",
			"city_code": "橿原市"
		},
		"6340821": {
			"postcode": "634-0821",
			"prefecture_name": "Nara-ken",
			"city_name": "Kashihara-shi",
			"ward_name": "",
			"town_name": "Nishiikejiricho",
			"building_name": "",
			"organization_name": "",
			"translations": {
				"ja": {
					"prefecture_name": "奈良県",
					"city_name": "橿原市",
					"ward_name": "",
					"town_name": "西池尻町",
					"building_name": "",
					"organization_name": ""
				}
			},
			"region_code": "関西",
			"prefecture_code": "奈良県",
			"city_code": "橿原市"
		},
		"6340817": {
			"postcode": "634-0817",
			"prefecture_name": "Nara-ken",
			"city_name": "Kashihara-shi",
			"ward_name": "",
			"town_name": "Teradacho",
			"building_name": "",
			"organization_name": "",
			"translations": {
				"ja": {
					"prefecture_name": "奈良県",
					"city_name": "橿原市",
					"ward_name": "",
					"town_name": "寺田町",
					"building_name": "",
					"organization_name": ""
				}
			},
			"region_code": "関西",
			"prefecture_code": "奈良県",
			"city_code": "橿原市"
		},
		"6340816": {
			"postcode": "634-0816",
			"prefecture_name": "Nara-ken",
			"city_name": "Kashihara-shi",
			"ward_name": "",
			"town_name": "Jimyojicho",
			"building_name": "",
			"organization_name": "",
			"translations": {
				"ja": {
					"prefecture_name": "奈良県",
					"city_name": "橿原市",
					"ward_name": "",
					"town_name": "慈明寺町",
					"building_name": "",
					"organization_name": ""
				}
			},
			"region_code": "関西",
			"prefecture_code": "奈良県",
			"city_code": "橿原市"
		},
		"6340815": {
			"postcode": "634-0815",
			"prefecture_name": "Nara-ken",
			"city_name": "Kashihara-shi",
			"ward_name": "",
			"town_name": "Otanicho",
			"building_name": "",
			"organization_name": "",
			"translations": {
				"ja": {
					"prefecture_name": "奈良県",
					"city_name": "橿原市",
					"ward_name": "",
					"town_name": "大谷町",
					"building_name": "",
					"organization_name": ""
				}
			},
			"region_code": "関西",
			"prefecture_code": "奈良県",
			"city_code": "橿原市"
		},
		"6340814": {
			"postcode": "634-0814",
			"prefecture_name": "Nara-ken",
			"city_name": "Kashihara-shi",
			"ward_name": "",
			"town_name": "Yamamotocho",
			"building_name": "",
			"organization_name": "",
			"translations": {
				"ja": {
					"prefecture_name": "奈良県",
					"city_name": "橿原市",
					"ward_name": "",
					"town_name": "山本町",
					"building_name": "",
					"organization_name": ""
				}
			},
			"region_code": "関西",
			"prefecture_code": "奈良県",
			"city_code": "橿原市"
		},
		"6340813": {
			"postcode": "634-0813",
			"prefecture_name": "Nara-ken",
			"city_name": "Kashihara-shi",
			"ward_name": "",
			"town_name": "Shijocho",
			"building_name": "",
			"organization_name": "",
			"translations": {
				"ja": {
					"prefecture_name": "奈良県",
					"city_name": "橿原市",
					"ward_name": "",
					"town_name": "四条町",
					"building_name": "",
					"organization_name": ""
				}
			},
			"region_code": "関西",
			"prefecture_code": "奈良県",
			"city_code": "橿原市"
		},
		"6340812": {
			"postcode": "634-0812",
			"prefecture_name": "Nara-ken",
			"city_name": "Kashihara-shi",
			"ward_name": "",
			"town_name": "Imaicho",
			"building_name": "",
			"organization_name": "",
			"translations": {
				"ja": {
					"prefecture_name": "奈良県",
					"city_name": "橿原市",
					"ward_name": "",
					"town_name": "今井町",
					"building_name": "",
					"organization_name": ""
				}
			},
			"region_code": "関西",
			"prefecture_code": "奈良県",
			"city_code": "橿原市"
		},
		"6340811": {
			"postcode": "634-0811",
			"prefecture_name": "Nara-ken",
			"city_name": "Kashihara-shi",
			"ward_name": "",
			"town_name": "Shokocho",
			"building_name": "",
			"organization_name": "",
			"translations": {
				"ja": {
					"prefecture_name": "奈良県",
					"city_name": "橿原市",
					"ward_name": "",
					"town_name": "小綱町",
					"building_name": "",
					"organization_name": ""
				}
			},
			"region_code": "関西",
			"prefecture_code": "奈良県",
			"city_code": "橿原市"
		},
		"6340805": {
			"postcode": "634-0805",
			"prefecture_name": "Nara-ken",
			"city_name": "Kashihara-shi",
			"ward_name": "",
			"town_name": "Jiocho",
			"building_name": "",
			"organization_name": "",
			"translations": {
				"ja": {
					"prefecture_name": "奈良県",
					"city_name": "橿原市",
					"ward_name": "",
					"town_name": "地黄町",
					"building_name": "",
					"organization_name": ""
				}
			},
			"region_code": "関西",
			"prefecture_code": "奈良県",
			"city_code": "橿原市"
		},
		"6340804": {
			"postcode": "634-0804",
			"prefecture_name": "Nara-ken",
			"city_name": "Kashihara-shi",
			"ward_name": "",
			"town_name": "Naizencho",
			"building_name": "",
			"organization_name": "",
			"translations": {
				"ja": {
					"prefecture_name": "奈良県",
					"city_name": "橿原市",
					"ward_name": "",
					"town_name": "内膳町",
					"building_name": "",
					"organization_name": ""
				}
			},
			"region_code": "関西",
			"prefecture_code": "奈良県",
			"city_code": "橿原市"
		},
		"6340803": {
			"postcode": "634-0803",
			"prefecture_name": "Nara-ken",
			"city_name": "Kashihara-shi",
			"ward_name": "",
			"town_name": "Jobonjicho",
			"building_name": "",
			"organization_name": "",
			"translations": {
				"ja": {
					"prefecture_name": "奈良県",
					"city_name": "橿原市",
					"ward_name": "",
					"town_name": "上品寺町",
					"building_name": "",
					"organization_name": ""
				}
			},
			"region_code": "関西",
			"prefecture_code": "奈良県",
			"city_code": "橿原市"
		},
		"6340802": {
			"postcode": "634-0802",
			"prefecture_name": "Nara-ken",
			"city_name": "Kashihara-shi",
			"ward_name": "",
			"town_name": "Ninokuchicho",
			"building_name": "",
			"organization_name": "",
			"translations": {
				"ja": {
					"prefecture_name": "奈良県",
					"city_name": "橿原市",
					"ward_name": "",
					"town_name": "新口町",
					"building_name": "",
					"organization_name": ""
				}
			},
			"region_code": "関西",
			"prefecture_code": "奈良県",
			"city_code": "橿原市"
		},
		"6340801": {
			"postcode": "634-0801",
			"prefecture_name": "Nara-ken",
			"city_name": "Kashihara-shi",
			"ward_name": "",
			"town_name": "Nishishindocho",
			"building_name": "",
			"organization_name": "",
			"translations": {
				"ja": {
					"prefecture_name": "奈良県",
					"city_name": "橿原市",
					"ward_name": "",
					"town_name": "西新堂町",
					"building_name": "",
					"organization_name": ""
				}
			},
			"region_code": "関西",
			"prefecture_code": "奈良県",
			"city_code": "橿原市"
		},
		"6340145": {
			"postcode": "634-0145",
			"prefecture_name": "Nara-ken",
			"city_name": "Takaichi-gun",
			"ward_name": "Asuka-mura",
			"town_name": "Noguchi",
			"building_name": "",
			"organization_name": "",
			"translations": {
				"ja": {
					"prefecture_name": "奈良県",
					"city_name": "高市郡",
					"ward_name": "明日香村",
					"town_name": "野口",
					"building_name": "",
					"organization_name": ""
				}
			},
			"region_code": "関西",
			"prefecture_code": "奈良県",
			"city_code": "高市郡"
		},
		"6340144": {
			"postcode": "634-0144",
			"prefecture_name": "Nara-ken",
			"city_name": "Takaichi-gun",
			"ward_name": "Asuka-mura",
			"town_name": "Hirata",
			"building_name": "",
			"organization_name": "",
			"translations": {
				"ja": {
					"prefecture_name": "奈良県",
					"city_name": "高市郡",
					"ward_name": "明日香村",
					"town_name": "平田",
					"building_name": "",
					"organization_name": ""
				}
			},
			"region_code": "関西",
			"prefecture_code": "奈良県",
			"city_code": "高市郡"
		},
		"6340143": {
			"postcode": "634-0143",
			"prefecture_name": "Nara-ken",
			"city_name": "Takaichi-gun",
			"ward_name": "Asuka-mura",
			"town_name": "Tachibe",
			"building_name": "",
			"organization_name": "",
			"translations": {
				"ja": {
					"prefecture_name": "奈良県",
					"city_name": "高市郡",
					"ward_name": "明日香村",
					"town_name": "立部",
					"building_name": "",
					"organization_name": ""
				}
			},
			"region_code": "関西",
			"prefecture_code": "奈良県",
			"city_code": "高市郡"
		},
		"6340142": {
			"postcode": "634-0142",
			"prefecture_name": "Nara-ken",
			"city_name": "Takaichi-gun",
			"ward_name": "Asuka-mura",
			"town_name": "Tachibana",
			"building_name": "",
			"organization_name": "",
			"translations": {
				"ja": {
					"prefecture_name": "奈良県",
					"city_name": "高市郡",
					"ward_name": "明日香村",
					"town_name": "橘",
					"building_name": "",
					"organization_name": ""
				}
			},
			"region_code": "関西",
			"prefecture_code": "奈良県",
			"city_code": "高市郡"
		},
		"6340141": {
			"postcode": "634-0141",
			"prefecture_name": "Nara-ken",
			"city_name": "Takaichi-gun",
			"ward_name": "Asuka-mura",
			"town_name": "Kawahara",
			"building_name": "",
			"organization_name": "",
			"translations": {
				"ja": {
					"prefecture_name": "奈良県",
					"city_name": "高市郡",
					"ward_name": "明日香村",
					"town_name": "川原",
					"building_name": "",
					"organization_name": ""
				}
			},
			"region_code": "関西",
			"prefecture_code": "奈良県",
			"city_code": "高市郡"
		},
		"6340138": {
			"postcode": "634-0138",
			"prefecture_name": "Nara-ken",
			"city_name": "Takaichi-gun",
			"ward_name": "Asuka-mura",
			"town_name": "Koshi",
			"building_name": "",
			"organization_name": "",
			"translations": {
				"ja": {
					"prefecture_name": "奈良県",
					"city_name": "高市郡",
					"ward_name": "明日香村",
					"town_name": "越",
					"building_name": "",
					"organization_name": ""
				}
			},
			"region_code": "関西",
			"prefecture_code": "奈良県",
			"city_code": "高市郡"
		},
		"6340137": {
			"postcode": "634-0137",
			"prefecture_name": "Nara-ken",
			"city_name": "Takaichi-gun",
			"ward_name": "Asuka-mura",
			"town_name": "Mayumi",
			"building_name": "",
			"organization_name": "",
			"translations": {
				"ja": {
					"prefecture_name": "奈良県",
					"city_name": "高市郡",
					"ward_name": "明日香村",
					"town_name": "真弓",
					"building_name": "",
					"organization_name": ""
				}
			},
			"region_code": "関西",
			"prefecture_code": "奈良県",
			"city_code": "高市郡"
		},
		"6340136": {
			"postcode": "634-0136",
			"prefecture_name": "Nara-ken",
			"city_name": "Takaichi-gun",
			"ward_name": "Asuka-mura",
			"town_name": "Jinokubo",
			"building_name": "",
			"organization_name": "",
			"translations": {
				"ja": {
					"prefecture_name": "奈良県",
					"city_name": "高市郡",
					"ward_name": "明日香村",
					"town_name": "地ノ窪",
					"building_name": "",
					"organization_name": ""
				}
			},
			"region_code": "関西",
			"prefecture_code": "奈良県",
			"city_code": "高市郡"
		},
		"6340135": {
			"postcode": "634-0135",
			"prefecture_name": "Nara-ken",
			"city_name": "Takaichi-gun",
			"ward_name": "Asuka-mura",
			"town_name": "Hinokuma",
			"building_name": "",
			"organization_name": "",
			"translations": {
				"ja": {
					"prefecture_name": "奈良県",
					"city_name": "高市郡",
					"ward_name": "明日香村",
					"town_name": "檜前",
					"building_name": "",
					"organization_name": ""
				}
			},
			"region_code": "関西",
			"prefecture_code": "奈良県",
			"city_code": "高市郡"
		},
		"6340134": {
			"postcode": "634-0134",
			"prefecture_name": "Nara-ken",
			"city_name": "Takaichi-gun",
			"ward_name": "Asuka-mura",
			"town_name": "Abeyama",
			"building_name": "",
			"organization_name": "",
			"translations": {
				"ja": {
					"prefecture_name": "奈良県",
					"city_name": "高市郡",
					"ward_name": "明日香村",
					"town_name": "阿部山",
					"building_name": "",
					"organization_name": ""
				}
			},
			"region_code": "関西",
			"prefecture_code": "奈良県",
			"city_code": "高市郡"
		},
		"6340133": {
			"postcode": "634-0133",
			"prefecture_name": "Nara-ken",
			"city_name": "Takaichi-gun",
			"ward_name": "Asuka-mura",
			"town_name": "Oneda",
			"building_name": "",
			"organization_name": "",
			"translations": {
				"ja": {
					"prefecture_name": "奈良県",
					"city_name": "高市郡",
					"ward_name": "明日香村",
					"town_name": "大根田",
					"building_name": "",
					"organization_name": ""
				}
			},
			"region_code": "関西",
			"prefecture_code": "奈良県",
			"city_code": "高市郡"
		},
		"6340132": {
			"postcode": "634-0132",
			"prefecture_name": "Nara-ken",
			"city_name": "Takaichi-gun",
			"ward_name": "Asuka-mura",
			"town_name": "Kurihara",
			"building_name": "",
			"organization_name": "",
			"translations": {
				"ja": {
					"prefecture_name": "奈良県",
					"city_name": "高市郡",
					"ward_name": "明日香村",
					"town_name": "栗原",
					"building_name": "",
					"organization_name": ""
				}
			},
			"region_code": "関西",
			"prefecture_code": "奈良県",
			"city_code": "高市郡"
		},
		"6340131": {
			"postcode": "634-0131",
			"prefecture_name": "Nara-ken",
			"city_name": "Takaichi-gun",
			"ward_name": "Asuka-mura",
			"town_name": "Misono",
			"building_name": "",
			"organization_name": "",
			"translations": {
				"ja": {
					"prefecture_name": "奈良県",
					"city_name": "高市郡",
					"ward_name": "明日香村",
					"town_name": "御園",
					"building_name": "",
					"organization_name": ""
				}
			},
			"region_code": "関西",
			"prefecture_code": "奈良県",
			"city_code": "高市郡"
		},
		"6340125": {
			"postcode": "634-0125",
			"prefecture_name": "Nara-ken",
			"city_name": "Takaichi-gun",
			"ward_name": "Asuka-mura",
			"town_name": "Nyudani",
			"building_name": "",
			"organization_name": "",
			"translations": {
				"ja": {
					"prefecture_name": "奈良県",
					"city_name": "高市郡",
					"ward_name": "明日香村",
					"town_name": "入谷",
					"building_name": "",
					"organization_name": ""
				}
			},
			"region_code": "関西",
			"prefecture_code": "奈良県",
			"city_code": "高市郡"
		},
		"6340124": {
			"postcode": "634-0124",
			"prefecture_name": "Nara-ken",
			"city_name": "Takaichi-gun",
			"ward_name": "Asuka-mura",
			"town_name": "Kayamori",
			"building_name": "",
			"organization_name": "",
			"translations": {
				"ja": {
					"prefecture_name": "奈良県",
					"city_name": "高市郡",
					"ward_name": "明日香村",
					"town_name": "栢森",
					"building_name": "",
					"organization_name": ""
				}
			},
			"region_code": "関西",
			"prefecture_code": "奈良県",
			"city_code": "高市郡"
		},
		"6340123": {
			"postcode": "634-0123",
			"prefecture_name": "Nara-ken",
			"city_name": "Takaichi-gun",
			"ward_name": "Asuka-mura",
			"town_name": "Inabuchi",
			"building_name": "",
			"organization_name": "",
			"translations": {
				"ja": {
					"prefecture_name": "奈良県",
					"city_name": "高市郡",
					"ward_name": "明日香村",
					"town_name": "稲渕",
					"building_name": "",
					"organization_name": ""
				}
			},
			"region_code": "関西",
			"prefecture_code": "奈良県",
			"city_code": "高市郡"
		},
		"6340122": {
			"postcode": "634-0122",
			"prefecture_name": "Nara-ken",
			"city_name": "Takaichi-gun",
			"ward_name": "Asuka-mura",
			"town_name": "Sakada",
			"building_name": "",
			"organization_name": "",
			"translations": {
				"ja": {
					"prefecture_name": "奈良県",
					"city_name": "高市郡",
					"ward_name": "明日香村",
					"town_name": "阪田",
					"building_name": "",
					"organization_name": ""
				}
			},
			"region_code": "関西",
			"prefecture_code": "奈良県",
			"city_code": "高市郡"
		},
		"6340121": {
			"postcode": "634-0121",
			"prefecture_name": "Nara-ken",
			"city_name": "Takaichi-gun",
			"ward_name": "Asuka-mura",
			"town_name": "Iwaido",
			"building_name": "",
			"organization_name": "",
			"translations": {
				"ja": {
					"prefecture_name": "奈良県",
					"city_name": "高市郡",
					"ward_name": "明日香村",
					"town_name": "祝戸",
					"building_name": "",
					"organization_name": ""
				}
			},
			"region_code": "関西",
			"prefecture_code": "奈良県",
			"city_code": "高市郡"
		},
		"6340118": {
			"postcode": "634-0118",
			"prefecture_name": "Nara-ken",
			"city_name": "Takaichi-gun",
			"ward_name": "Asuka-mura",
			"town_name": "Hata",
			"building_name": "",
			"organization_name": "",
			"translations": {
				"ja": {
					"prefecture_name": "奈良県",
					"city_name": "高市郡",
					"ward_name": "明日香村",
					"town_name": "畑",
					"building_name": "",
					"organization_name": ""
				}
			},
			"region_code": "関西",
			"prefecture_code": "奈良県",
			"city_code": "高市郡"
		},
		"6340117": {
			"postcode": "634-0117",
			"prefecture_name": "Nara-ken",
			"city_name": "Takaichi-gun",
			"ward_name": "Asuka-mura",
			"town_name": "Fuyuno",
			"building_name": "",
			"organization_name": "",
			"translations": {
				"ja": {
					"prefecture_name": "奈良県",
					"city_name": "高市郡",
					"ward_name": "明日香村",
					"town_name": "冬野",
					"building_name": "",
					"organization_name": ""
				}
			},
			"region_code": "関西",
			"prefecture_code": "奈良県",
			"city_code": "高市郡"
		},
		"6340116": {
			"postcode": "634-0116",
			"prefecture_name": "Nara-ken",
			"city_name": "Takaichi-gun",
			"ward_name": "Asuka-mura",
			"town_name": "Oso",
			"building_name": "",
			"organization_name": "",
			"translations": {
				"ja": {
					"prefecture_name": "奈良県",
					"city_name": "高市郡",
					"ward_name": "明日香村",
					"town_name": "尾曽",
					"building_name": "",
					"organization_name": ""
				}
			},
			"region_code": "関西",
			"prefecture_code": "奈良県",
			"city_code": "高市郡"
		},
		"6340115": {
			"postcode": "634-0115",
			"prefecture_name": "Nara-ken",
			"city_name": "Takaichi-gun",
			"ward_name": "Asuka-mura",
			"town_name": "Kamura",
			"building_name": "",
			"organization_name": "",
			"translations": {
				"ja": {
					"prefecture_name": "奈良県",
					"city_name": "高市郡",
					"ward_name": "明日香村",
					"town_name": "上",
					"building_name": "",
					"organization_name": ""
				}
			},
			"region_code": "関西",
			"prefecture_code": "奈良県",
			"city_code": "高市郡"
		},
		"6340114": {
			"postcode": "634-0114",
			"prefecture_name": "Nara-ken",
			"city_name": "Takaichi-gun",
			"ward_name": "Asuka-mura",
			"town_name": "Hosokawa",
			"building_name": "",
			"organization_name": "",
			"translations": {
				"ja": {
					"prefecture_name": "奈良県",
					"city_name": "高市郡",
					"ward_name": "明日香村",
					"town_name": "細川",
					"building_name": "",
					"organization_name": ""
				}
			},
			"region_code": "関西",
			"prefecture_code": "奈良県",
			"city_code": "高市郡"
		},
		"6340113": {
			"postcode": "634-0113",
			"prefecture_name": "Nara-ken",
			"city_name": "Takaichi-gun",
			"ward_name": "Asuka-mura",
			"town_name": "Jogo",
			"building_name": "",
			"organization_name": "",
			"translations": {
				"ja": {
					"prefecture_name": "奈良県",
					"city_name": "高市郡",
					"ward_name": "明日香村",
					"town_name": "上居",
					"building_name": "",
					"organization_name": ""
				}
			},
			"region_code": "関西",
			"prefecture_code": "奈良県",
			"city_code": "高市郡"
		},
		"6340112": {
			"postcode": "634-0112",
			"prefecture_name": "Nara-ken",
			"city_name": "Takaichi-gun",
			"ward_name": "Asuka-mura",
			"town_name": "Shimasho",
			"building_name": "",
			"organization_name": "",
			"translations": {
				"ja": {
					"prefecture_name": "奈良県",
					"city_name": "高市郡",
					"ward_name": "明日香村",
					"town_name": "島庄",
					"building_name": "",
					"organization_name": ""
				}
			},
			"region_code": "関西",
			"prefecture_code": "奈良県",
			"city_code": "高市郡"
		},
		"6340111": {
			"postcode": "634-0111",
			"prefecture_name": "Nara-ken",
			"city_name": "Takaichi-gun",
			"ward_name": "Asuka-mura",
			"town_name": "Oka",
			"building_name": "",
			"organization_name": "",
			"translations": {
				"ja": {
					"prefecture_name": "奈良県",
					"city_name": "高市郡",
					"ward_name": "明日香村",
					"town_name": "岡",
					"building_name": "",
					"organization_name": ""
				}
			},
			"region_code": "関西",
			"prefecture_code": "奈良県",
			"city_code": "高市郡"
		},
		"6340108": {
			"postcode": "634-0108",
			"prefecture_name": "Nara-ken",
			"city_name": "Takaichi-gun",
			"ward_name": "Asuka-mura",
			"town_name": "Ikatsuchi",
			"building_name": "",
			"organization_name": "",
			"translations": {
				"ja": {
					"prefecture_name": "奈良県",
					"city_name": "高市郡",
					"ward_name": "明日香村",
					"town_name": "雷",
					"building_name": "",
					"organization_name": ""
				}
			},
			"region_code": "関西",
			"prefecture_code": "奈良県",
			"city_code": "高市郡"
		},
		"6340107": {
			"postcode": "634-0107",
			"prefecture_name": "Nara-ken",
			"city_name": "Takaichi-gun",
			"ward_name": "Asuka-mura",
			"town_name": "Toyora",
			"building_name": "",
			"organization_name": "",
			"translations": {
				"ja": {
					"prefecture_name": "奈良県",
					"city_name": "高市郡",
					"ward_name": "明日香村",
					"town_name": "豊浦",
					"building_name": "",
					"organization_name": ""
				}
			},
			"region_code": "関西",
			"prefecture_code": "奈良県",
			"city_code": "高市郡"
		},
		"6340106": {
			"postcode": "634-0106",
			"prefecture_name": "Nara-ken",
			"city_name": "Takaichi-gun",
			"ward_name": "Asuka-mura",
			"town_name": "Ohara",
			"building_name": "",
			"organization_name": "",
			"translations": {
				"ja": {
					"prefecture_name": "奈良県",
					"city_name": "高市郡",
					"ward_name": "明日香村",
					"town_name": "小原",
					"building_name": "",
					"organization_name": ""
				}
			},
			"region_code": "関西",
			"prefecture_code": "奈良県",
			"city_code": "高市郡"
		},
		"6340105": {
			"postcode": "634-0105",
			"prefecture_name": "Nara-ken",
			"city_name": "Takaichi-gun",
			"ward_name": "Asuka-mura",
			"town_name": "Higashiyama",
			"building_name": "",
			"organization_name": "",
			"translations": {
				"ja": {
					"prefecture_name": "奈良県",
					"city_name": "高市郡",
					"ward_name": "明日香村",
					"town_name": "東山",
					"building_name": "",
					"organization_name": ""
				}
			},
			"region_code": "関西",
			"prefecture_code": "奈良県",
			"city_code": "高市郡"
		},
		"6340104": {
			"postcode": "634-0104",
			"prefecture_name": "Nara-ken",
			"city_name": "Takaichi-gun",
			"ward_name": "Asuka-mura",
			"town_name": "Yatsuri",
			"building_name": "",
			"organization_name": "",
			"translations": {
				"ja": {
					"prefecture_name": "奈良県",
					"city_name": "高市郡",
					"ward_name": "明日香村",
					"town_name": "八釣",
					"building_name": "",
					"organization_name": ""
				}
			},
			"region_code": "関西",
			"prefecture_code": "奈良県",
			"city_code": "高市郡"
		},
		"6340103": {
			"postcode": "634-0103",
			"prefecture_name": "Nara-ken",
			"city_name": "Takaichi-gun",
			"ward_name": "Asuka-mura",
			"town_name": "Asuka",
			"building_name": "",
			"organization_name": "",
			"translations": {
				"ja": {
					"prefecture_name": "奈良県",
					"city_name": "高市郡",
					"ward_name": "明日香村",
					"town_name": "飛鳥",
					"building_name": "",
					"organization_name": ""
				}
			},
			"region_code": "関西",
			"prefecture_code": "奈良県",
			"city_code": "高市郡"
		},
		"6340102": {
			"postcode": "634-0102",
			"prefecture_name": "Nara-ken",
			"city_name": "Takaichi-gun",
			"ward_name": "Asuka-mura",
			"town_name": "Okuyama",
			"building_name": "",
			"organization_name": "",
			"translations": {
				"ja": {
					"prefecture_name": "奈良県",
					"city_name": "高市郡",
					"ward_name": "明日香村",
					"town_name": "奥山",
					"building_name": "",
					"organization_name": ""
				}
			},
			"region_code": "関西",
			"prefecture_code": "奈良県",
			"city_code": "高市郡"
		},
		"6340101": {
			"postcode": "634-0101",
			"prefecture_name": "Nara-ken",
			"city_name": "Takaichi-gun",
			"ward_name": "Asuka-mura",
			"town_name": "Koyama",
			"building_name": "",
			"organization_name": "",
			"translations": {
				"ja": {
					"prefecture_name": "奈良県",
					"city_name": "高市郡",
					"ward_name": "明日香村",
					"town_name": "小山",
					"building_name": "",
					"organization_name": ""
				}
			},
			"region_code": "関西",
			"prefecture_code": "奈良県",
			"city_code": "高市郡"
		},
		"6340100": {
			"postcode": "634-0100",
			"prefecture_name": "Nara-ken",
			"city_name": "Takaichi-gun",
			"ward_name": "Asuka-mura",
			"town_name": "",
			"building_name": "",
			"organization_name": "",
			"translations": {
				"ja": {
					"prefecture_name": "奈良県",
					"city_name": "高市郡",
					"ward_name": "明日香村",
					"town_name": "",
					"building_name": "",
					"organization_name": ""
				}
			},
			"region_code": "関西",
			"prefecture_code": "奈良県",
			"city_code": "高市郡"
		},
		"6340078": {
			"postcode": "634-0078",
			"prefecture_name": "Nara-ken",
			"city_name": "Kashihara-shi",
			"ward_name": "",
			"town_name": "Yagicho",
			"building_name": "",
			"organization_name": "",
			"translations": {
				"ja": {
					"prefecture_name": "奈良県",
					"city_name": "橿原市",
					"ward_name": "",
					"town_name": "八木町",
					"building_name": "",
					"organization_name": ""
				}
			},
			"region_code": "関西",
			"prefecture_code": "奈良県",
			"city_code": "橿原市"
		},
		"6340077": {
			"postcode": "634-0077",
			"prefecture_name": "Nara-ken",
			"city_name": "Kashihara-shi",
			"ward_name": "",
			"town_name": "Minamiyagicho",
			"building_name": "",
			"organization_name": "",
			"translations": {
				"ja": {
					"prefecture_name": "奈良県",
					"city_name": "橿原市",
					"ward_name": "",
					"town_name": "南八木町",
					"building_name": "",
					"organization_name": ""
				}
			},
			"region_code": "関西",
			"prefecture_code": "奈良県",
			"city_code": "橿原市"
		},
		"6340076": {
			"postcode": "634-0076",
			"prefecture_name": "Nara-ken",
			"city_name": "Kashihara-shi",
			"ward_name": "",
			"town_name": "Hyobucho",
			"building_name": "",
			"organization_name": "",
			"translations": {
				"ja": {
					"prefecture_name": "奈良県",
					"city_name": "橿原市",
					"ward_name": "",
					"town_name": "兵部町",
					"building_name": "",
					"organization_name": ""
				}
			},
			"region_code": "関西",
			"prefecture_code": "奈良県",
			"city_code": "橿原市"
		},
		"6340075": {
			"postcode": "634-0075",
			"prefecture_name": "Nara-ken",
			"city_name": "Kashihara-shi",
			"ward_name": "",
			"town_name": "Osacho",
			"building_name": "",
			"organization_name": "",
			"translations": {
				"ja": {
					"prefecture_name": "奈良県",
					"city_name": "橿原市",
					"ward_name": "",
					"town_name": "小房町",
					"building_name": "",
					"organization_name": ""
				}
			},
			"region_code": "関西",
			"prefecture_code": "奈良県",
			"city_code": "橿原市"
		},
		"6340074": {
			"postcode": "634-0074",
			"prefecture_name": "Nara-ken",
			"city_name": "Kashihara-shi",
			"ward_name": "",
			"town_name": "Shibucho",
			"building_name": "",
			"organization_name": "",
			"translations": {
				"ja": {
					"prefecture_name": "奈良県",
					"city_name": "橿原市",
					"ward_name": "",
					"town_name": "四分町",
					"building_name": "",
					"organization_name": ""
				}
			},
			"region_code": "関西",
			"prefecture_code": "奈良県",
			"city_code": "橿原市"
		},
		"6340073": {
			"postcode": "634-0073",
			"prefecture_name": "Nara-ken",
			"city_name": "Kashihara-shi",
			"ward_name": "",
			"town_name": "Nawatecho",
			"building_name": "",
			"organization_name": "",
			"translations": {
				"ja": {
					"prefecture_name": "奈良県",
					"city_name": "橿原市",
					"ward_name": "",
					"town_name": "縄手町",
					"building_name": "",
					"organization_name": ""
				}
			},
			"region_code": "関西",
			"prefecture_code": "奈良県",
			"city_code": "橿原市"
		},
		"6340072": {
			"postcode": "634-0072",
			"prefecture_name": "Nara-ken",
			"city_name": "Kashihara-shi",
			"ward_name": "",
			"town_name": "Daigocho",
			"building_name": "",
			"organization_name": "",
			"translations": {
				"ja": {
					"prefecture_name": "奈良県",
					"city_name": "橿原市",
					"ward_name": "",
					"town_name": "醍醐町",
					"building_name": "",
					"organization_name": ""
				}
			},
			"region_code": "関西",
			"prefecture_code": "奈良県",
			"city_code": "橿原市"
		},
		"6340071": {
			"postcode": "634-0071",
			"prefecture_name": "Nara-ken",
			"city_name": "Kashihara-shi",
			"ward_name": "",
			"town_name": "Yamanobocho",
			"building_name": "",
			"organization_name": "",
			"translations": {
				"ja": {
					"prefecture_name": "奈良県",
					"city_name": "橿原市",
					"ward_name": "",
					"town_name": "山之坊町",
					"building_name": "",
					"organization_name": ""
				}
			},
			"region_code": "関西",
			"prefecture_code": "奈良県",
			"city_code": "橿原市"
		},
		"6340065": {
			"postcode": "634-0065",
			"prefecture_name": "Nara-ken",
			"city_name": "Kashihara-shi",
			"ward_name": "",
			"town_name": "Unebicho",
			"building_name": "",
			"organization_name": "",
			"translations": {
				"ja": {
					"prefecture_name": "奈良県",
					"city_name": "橿原市",
					"ward_name": "",
					"town_name": "畝傍町",
					"building_name": "",
					"organization_name": ""
				}
			},
			"region_code": "関西",
			"prefecture_code": "奈良県",
			"city_code": "橿原市"
		},
		"6340064": {
			"postcode": "634-0064",
			"prefecture_name": "Nara-ken",
			"city_name": "Kashihara-shi",
			"ward_name": "",
			"town_name": "Misecho",
			"building_name": "",
			"organization_name": "",
			"translations": {
				"ja": {
					"prefecture_name": "奈良県",
					"city_name": "橿原市",
					"ward_name": "",
					"town_name": "見瀬町",
					"building_name": "",
					"organization_name": ""
				}
			},
			"region_code": "関西",
			"prefecture_code": "奈良県",
			"city_code": "橿原市"
		},
		"6340063": {
			"postcode": "634-0063",
			"prefecture_name": "Nara-ken",
			"city_name": "Kashihara-shi",
			"ward_name": "",
			"town_name": "Kumecho",
			"building_name": "",
			"organization_name": "",
			"translations": {
				"ja": {
					"prefecture_name": "奈良県",
					"city_name": "橿原市",
					"ward_name": "",
					"town_name": "久米町",
					"building_name": "",
					"organization_name": ""
				}
			},
			"region_code": "関西",
			"prefecture_code": "奈良県",
			"city_code": "橿原市"
		},
		"6340062": {
			"postcode": "634-0062",
			"prefecture_name": "Nara-ken",
			"city_name": "Kashihara-shi",
			"ward_name": "",
			"town_name": "Gobocho",
			"building_name": "",
			"organization_name": "",
			"translations": {
				"ja": {
					"prefecture_name": "奈良県",
					"city_name": "橿原市",
					"ward_name": "",
					"town_name": "御坊町",
					"building_name": "",
					"organization_name": ""
				}
			},
			"region_code": "関西",
			"prefecture_code": "奈良県",
			"city_code": "橿原市"
		},
		"6340061": {
			"postcode": "634-0061",
			"prefecture_name": "Nara-ken",
			"city_name": "Kashihara-shi",
			"ward_name": "",
			"town_name": "Okubocho",
			"building_name": "",
			"organization_name": "",
			"translations": {
				"ja": {
					"prefecture_name": "奈良県",
					"city_name": "橿原市",
					"ward_name": "",
					"town_name": "大久保町",
					"building_name": "",
					"organization_name": ""
				}
			},
			"region_code": "関西",
			"prefecture_code": "奈良県",
			"city_code": "橿原市"
		},
		"6340052": {
			"postcode": "634-0052",
			"prefecture_name": "Nara-ken",
			"city_name": "Kashihara-shi",
			"ward_name": "",
			"town_name": "Minamimyohojicho",
			"building_name": "",
			"organization_name": "",
			"translations": {
				"ja": {
					"prefecture_name": "奈良県",
					"city_name": "橿原市",
					"ward_name": "",
					"town_name": "南妙法寺町",
					"building_name": "",
					"organization_name": ""
				}
			},
			"region_code": "関西",
			"prefecture_code": "奈良県",
			"city_code": "橿原市"
		},
		"6340051": {
			"postcode": "634-0051",
			"prefecture_name": "Nara-ken",
			"city_name": "Kashihara-shi",
			"ward_name": "",
			"town_name": "Shirakashicho",
			"building_name": "",
			"organization_name": "",
			"translations": {
				"ja": {
					"prefecture_name": "奈良県",
					"city_name": "橿原市",
					"ward_name": "",
					"town_name": "白橿町",
					"building_name": "",
					"organization_name": ""
				}
			},
			"region_code": "関西",
			"prefecture_code": "奈良県",
			"city_code": "橿原市"
		},
		"6340046": {
			"postcode": "634-0046",
			"prefecture_name": "Nara-ken",
			"city_name": "Kashihara-shi",
			"ward_name": "",
			"town_name": "Eiwacho",
			"building_name": "",
			"organization_name": "",
			"translations": {
				"ja": {
					"prefecture_name": "奈良県",
					"city_name": "橿原市",
					"ward_name": "",
					"town_name": "栄和町",
					"building_name": "",
					"organization_name": ""
				}
			},
			"region_code": "関西",
			"prefecture_code": "奈良県",
			"city_code": "橿原市"
		},
		"6340045": {
			"postcode": "634-0045",
			"prefecture_name": "Nara-ken",
			"city_name": "Kashihara-shi",
			"ward_name": "",
			"town_name": "Ishikawacho",
			"building_name": "",
			"organization_name": "",
			"translations": {
				"ja": {
					"prefecture_name": "奈良県",
					"city_name": "橿原市",
					"ward_name": "",
					"town_name": "石川町",
					"building_name": "",
					"organization_name": ""
				}
			},
			"region_code": "関西",
			"prefecture_code": "奈良県",
			"city_code": "橿原市"
		},
		"6340044": {
			"postcode": "634-0044",
			"prefecture_name": "Nara-ken",
			"city_name": "Kashihara-shi",
			"ward_name": "",
			"town_name": "Ogarucho",
			"building_name": "",
			"organization_name": "",
			"translations": {
				"ja": {
					"prefecture_name": "奈良県",
					"city_name": "橿原市",
					"ward_name": "",
					"town_name": "大軽町",
					"building_name": "",
					"organization_name": ""
				}
			},
			"region_code": "関西",
			"prefecture_code": "奈良県",
			"city_code": "橿原市"
		},
		"6340043": {
			"postcode": "634-0043",
			"prefecture_name": "Nara-ken",
			"city_name": "Kashihara-shi",
			"ward_name": "",
			"town_name": "Gojonocho",
			"building_name": "",
			"organization_name": "",
			"translations": {
				"ja": {
					"prefecture_name": "奈良県",
					"city_name": "橿原市",
					"ward_name": "",
					"town_name": "五条野町",
					"building_name": "",
					"organization_name": ""
				}
			},
			"region_code": "関西",
			"prefecture_code": "奈良県",
			"city_code": "橿原市"
		},
		"6340042": {
			"postcode": "634-0042",
			"prefecture_name": "Nara-ken",
			"city_name": "Kashihara-shi",
			"ward_name": "",
			"town_name": "Shobucho",
			"building_name": "",
			"organization_name": "",
			"translations": {
				"ja": {
					"prefecture_name": "奈良県",
					"city_name": "橿原市",
					"ward_name": "",
					"town_name": "菖蒲町",
					"building_name": "",
					"organization_name": ""
				}
			},
			"region_code": "関西",
			"prefecture_code": "奈良県",
			"city_code": "橿原市"
		},
		"6340041": {
			"postcode": "634-0041",
			"prefecture_name": "Nara-ken",
			"city_name": "Kashihara-shi",
			"ward_name": "",
			"town_name": "Wadacho",
			"building_name": "",
			"organization_name": "",
			"translations": {
				"ja": {
					"prefecture_name": "奈良県",
					"city_name": "橿原市",
					"ward_name": "",
					"town_name": "和田町",
					"building_name": "",
					"organization_name": ""
				}
			},
			"region_code": "関西",
			"prefecture_code": "奈良県",
			"city_code": "橿原市"
		},
		"6340034": {
			"postcode": "634-0034",
			"prefecture_name": "Nara-ken",
			"city_name": "Kashihara-shi",
			"ward_name": "",
			"town_name": "Hidacho",
			"building_name": "",
			"organization_name": "",
			"translations": {
				"ja": {
					"prefecture_name": "奈良県",
					"city_name": "橿原市",
					"ward_name": "",
					"town_name": "飛騨町",
					"building_name": "",
					"organization_name": ""
				}
			},
			"region_code": "関西",
			"prefecture_code": "奈良県",
			"city_code": "橿原市"
		},
		"6340033": {
			"postcode": "634-0033",
			"prefecture_name": "Nara-ken",
			"city_name": "Kashihara-shi",
			"ward_name": "",
			"town_name": "Kidonocho",
			"building_name": "",
			"organization_name": "",
			"translations": {
				"ja": {
					"prefecture_name": "奈良県",
					"city_name": "橿原市",
					"ward_name": "",
					"town_name": "城殿町",
					"building_name": "",
					"organization_name": ""
				}
			},
			"region_code": "関西",
			"prefecture_code": "奈良県",
			"city_code": "橿原市"
		},
		"6340032": {
			"postcode": "634-0032",
			"prefecture_name": "Nara-ken",
			"city_name": "Kashihara-shi",
			"ward_name": "",
			"town_name": "Tanakacho",
			"building_name": "",
			"organization_name": "",
			"translations": {
				"ja": {
					"prefecture_name": "奈良県",
					"city_name": "橿原市",
					"ward_name": "",
					"town_name": "田中町",
					"building_name": "",
					"organization_name": ""
				}
			},
			"region_code": "関西",
			"prefecture_code": "奈良県",
			"city_code": "橿原市"
		},
		"6340031": {
			"postcode": "634-0031",
			"prefecture_name": "Nara-ken",
			"city_name": "Kashihara-shi",
			"ward_name": "",
			"town_name": "Kamihidacho",
			"building_name": "",
			"organization_name": "",
			"translations": {
				"ja": {
					"prefecture_name": "奈良県",
					"city_name": "橿原市",
					"ward_name": "",
					"town_name": "上飛騨町",
					"building_name": "",
					"organization_name": ""
				}
			},
			"region_code": "関西",
			"prefecture_code": "奈良県",
			"city_code": "橿原市"
		},
		"6340029": {
			"postcode": "634-0029",
			"prefecture_name": "Nara-ken",
			"city_name": "Kashihara-shi",
			"ward_name": "",
			"town_name": "Shimoyatsuricho",
			"building_name": "",
			"organization_name": "",
			"translations": {
				"ja": {
					"prefecture_name": "奈良県",
					"city_name": "橿原市",
					"ward_name": "",
					"town_name": "下八釣町",
					"building_name": "",
					"organization_name": ""
				}
			},
			"region_code": "関西",
			"prefecture_code": "奈良県",
			"city_code": "橿原市"
		},
		"6340028": {
			"postcode": "634-0028",
			"prefecture_name": "Nara-ken",
			"city_name": "Kashihara-shi",
			"ward_name": "",
			"town_name": "Hokkeijicho",
			"building_name": "",
			"organization_name": "",
			"translations": {
				"ja": {
					"prefecture_name": "奈良県",
					"city_name": "橿原市",
					"ward_name": "",
					"town_name": "法花寺町",
					"building_name": "",
					"organization_name": ""
				}
			},
			"region_code": "関西",
			"prefecture_code": "奈良県",
			"city_code": "橿原市"
		},
		"6340027": {
			"postcode": "634-0027",
			"prefecture_name": "Nara-ken",
			"city_name": "Kashihara-shi",
			"ward_name": "",
			"town_name": "Takadonocho",
			"building_name": "",
			"organization_name": "",
			"translations": {
				"ja": {
					"prefecture_name": "奈良県",
					"city_name": "橿原市",
					"ward_name": "",
					"town_name": "高殿町",
					"building_name": "",
					"organization_name": ""
				}
			},
			"region_code": "関西",
			"prefecture_code": "奈良県",
			"city_code": "橿原市"
		},
		"6340026": {
			"postcode": "634-0026",
			"prefecture_name": "Nara-ken",
			"city_name": "Kashihara-shi",
			"ward_name": "",
			"town_name": "Besshiyocho",
			"building_name": "",
			"organization_name": "",
			"translations": {
				"ja": {
					"prefecture_name": "奈良県",
					"city_name": "橿原市",
					"ward_name": "",
					"town_name": "別所町",
					"building_name": "",
					"organization_name": ""
				}
			},
			"region_code": "関西",
			"prefecture_code": "奈良県",
			"city_code": "橿原市"
		},
		"6340025": {
			"postcode": "634-0025",
			"prefecture_name": "Nara-ken",
			"city_name": "Kashihara-shi",
			"ward_name": "",
			"town_name": "Kinomotocho",
			"building_name": "",
			"organization_name": "",
			"translations": {
				"ja": {
					"prefecture_name": "奈良県",
					"city_name": "橿原市",
					"ward_name": "",
					"town_name": "木之本町",
					"building_name": "",
					"organization_name": ""
				}
			},
			"region_code": "関西",
			"prefecture_code": "奈良県",
			"city_code": "橿原市"
		},
		"6340024": {
			"postcode": "634-0024",
			"prefecture_name": "Nara-ken",
			"city_name": "Kashihara-shi",
			"ward_name": "",
			"town_name": "Minamiyamacho",
			"building_name": "",
			"organization_name": "",
			"translations": {
				"ja": {
					"prefecture_name": "奈良県",
					"city_name": "橿原市",
					"ward_name": "",
					"town_name": "南山町",
					"building_name": "",
					"organization_name": ""
				}
			},
			"region_code": "関西",
			"prefecture_code": "奈良県",
			"city_code": "橿原市"
		},
		"6340023": {
			"postcode": "634-0023",
			"prefecture_name": "Nara-ken",
			"city_name": "Kashihara-shi",
			"ward_name": "",
			"town_name": "Kaigecho",
			"building_name": "",
			"organization_name": "",
			"translations": {
				"ja": {
					"prefecture_name": "奈良県",
					"city_name": "橿原市",
					"ward_name": "",
					"town_name": "戒外町",
					"building_name": "",
					"organization_name": ""
				}
			},
			"region_code": "関西",
			"prefecture_code": "奈良県",
			"city_code": "橿原市"
		},
		"6340022": {
			"postcode": "634-0022",
			"prefecture_name": "Nara-ken",
			"city_name": "Kashihara-shi",
			"ward_name": "",
			"town_name": "Minamiuracho",
			"building_name": "",
			"organization_name": "",
			"translations": {
				"ja": {
					"prefecture_name": "奈良県",
					"city_name": "橿原市",
					"ward_name": "",
					"town_name": "南浦町",
					"building_name": "",
					"organization_name": ""
				}
			},
			"region_code": "関西",
			"prefecture_code": "奈良県",
			"city_code": "橿原市"
		},
		"6340021": {
			"postcode": "634-0021",
			"prefecture_name": "Nara-ken",
			"city_name": "Kashihara-shi",
			"ward_name": "",
			"town_name": "Higashiikejiricho",
			"building_name": "",
			"organization_name": "",
			"translations": {
				"ja": {
					"prefecture_name": "奈良県",
					"city_name": "橿原市",
					"ward_name": "",
					"town_name": "東池尻町",
					"building_name": "",
					"organization_name": ""
				}
			},
			"region_code": "関西",
			"prefecture_code": "奈良県",
			"city_code": "橿原市"
		},
		"6340014": {
			"postcode": "634-0014",
			"prefecture_name": "Nara-ken",
			"city_name": "Kashihara-shi",
			"ward_name": "",
			"town_name": "Ishiharadacho",
			"building_name": "",
			"organization_name": "",
			"translations": {
				"ja": {
					"prefecture_name": "奈良県",
					"city_name": "橿原市",
					"ward_name": "",
					"town_name": "石原田町",
					"building_name": "",
					"organization_name": ""
				}
			},
			"region_code": "関西",
			"prefecture_code": "奈良県",
			"city_code": "橿原市"
		},
		"6340013": {
			"postcode": "634-0013",
			"prefecture_name": "Nara-ken",
			"city_name": "Kashihara-shi",
			"ward_name": "",
			"town_name": "Deaicho",
			"building_name": "",
			"organization_name": "",
			"translations": {
				"ja": {
					"prefecture_name": "奈良県",
					"city_name": "橿原市",
					"ward_name": "",
					"town_name": "出合町",
					"building_name": "",
					"organization_name": ""
				}
			},
			"region_code": "関西",
			"prefecture_code": "奈良県",
			"city_code": "橿原市"
		},
		"6340012": {
			"postcode": "634-0012",
			"prefecture_name": "Nara-ken",
			"city_name": "Kashihara-shi",
			"ward_name": "",
			"town_name": "Kashiwatecho",
			"building_name": "",
			"organization_name": "",
			"translations": {
				"ja": {
					"prefecture_name": "奈良県",
					"city_name": "橿原市",
					"ward_name": "",
					"town_name": "膳夫町",
					"building_name": "",
					"organization_name": ""
				}
			},
			"region_code": "関西",
			"prefecture_code": "奈良県",
			"city_code": "橿原市"
		},
		"6340011": {
			"postcode": "634-0011",
			"prefecture_name": "Nara-ken",
			"city_name": "Kashihara-shi",
			"ward_name": "",
			"town_name": "Degaitocho",
			"building_name": "",
			"organization_name": "",
			"translations": {
				"ja": {
					"prefecture_name": "奈良県",
					"city_name": "橿原市",
					"ward_name": "",
					"town_name": "出垣内町",
					"building_name": "",
					"organization_name": ""
				}
			},
			"region_code": "関西",
			"prefecture_code": "奈良県",
			"city_code": "橿原市"
		},
		"6340009": {
			"postcode": "634-0009",
			"prefecture_name": "Nara-ken",
			"city_name": "Kashihara-shi",
			"ward_name": "",
			"town_name": "Nakacho",
			"building_name": "",
			"organization_name": "",
			"translations": {
				"ja": {
					"prefecture_name": "奈良県",
					"city_name": "橿原市",
					"ward_name": "",
					"town_name": "中町",
					"building_name": "",
					"organization_name": ""
				}
			},
			"region_code": "関西",
			"prefecture_code": "奈良県",
			"city_code": "橿原市"
		},
		"6340008": {
			"postcode": "634-0008",
			"prefecture_name": "Nara-ken",
			"city_name": "Kashihara-shi",
			"ward_name": "",
			"town_name": "Toichicho",
			"building_name": "",
			"organization_name": "",
			"translations": {
				"ja": {
					"prefecture_name": "奈良県",
					"city_name": "橿原市",
					"ward_name": "",
					"town_name": "十市町",
					"building_name": "",
					"organization_name": ""
				}
			},
			"region_code": "関西",
			"prefecture_code": "奈良県",
			"city_code": "橿原市"
		},
		"6340007": {
			"postcode": "634-0007",
			"prefecture_name": "Nara-ken",
			"city_name": "Kashihara-shi",
			"ward_name": "",
			"town_name": "Kuzumotocho",
			"building_name": "",
			"organization_name": "",
			"translations": {
				"ja": {
					"prefecture_name": "奈良県",
					"city_name": "橿原市",
					"ward_name": "",
					"town_name": "葛本町",
					"building_name": "",
					"organization_name": ""
				}
			},
			"region_code": "関西",
			"prefecture_code": "奈良県",
			"city_code": "橿原市"
		},
		"6340006": {
			"postcode": "634-0006",
			"prefecture_name": "Nara-ken",
			"city_name": "Kashihara-shi",
			"ward_name": "",
			"town_name": "Shingacho",
			"building_name": "",
			"organization_name": "",
			"translations": {
				"ja": {
					"prefecture_name": "奈良県",
					"city_name": "橿原市",
					"ward_name": "",
					"town_name": "新賀町",
					"building_name": "",
					"organization_name": ""
				}
			},
			"region_code": "関西",
			"prefecture_code": "奈良県",
			"city_code": "橿原市"
		},
		"6340005": {
			"postcode": "634-0005",
			"prefecture_name": "Nara-ken",
			"city_name": "Kashihara-shi",
			"ward_name": "",
			"town_name": "Kitayagicho",
			"building_name": "",
			"organization_name": "",
			"translations": {
				"ja": {
					"prefecture_name": "奈良県",
					"city_name": "橿原市",
					"ward_name": "",
					"town_name": "北八木町",
					"building_name": "",
					"organization_name": ""
				}
			},
			"region_code": "関西",
			"prefecture_code": "奈良県",
			"city_code": "橿原市"
		},
		"6340004": {
			"postcode": "634-0004",
			"prefecture_name": "Nara-ken",
			"city_name": "Kashihara-shi",
			"ward_name": "",
			"town_name": "Kiharacho",
			"building_name": "",
			"organization_name": "",
			"translations": {
				"ja": {
					"prefecture_name": "奈良県",
					"city_name": "橿原市",
					"ward_name": "",
					"town_name": "木原町",
					"building_name": "",
					"organization_name": ""
				}
			},
			"region_code": "関西",
			"prefecture_code": "奈良県",
			"city_code": "橿原市"
		},
		"6340003": {
			"postcode": "634-0003",
			"prefecture_name": "Nara-ken",
			"city_name": "Kashihara-shi",
			"ward_name": "",
			"town_name": "Tokiwacho",
			"building_name": "",
			"organization_name": "",
			"translations": {
				"ja": {
					"prefecture_name": "奈良県",
					"city_name": "橿原市",
					"ward_name": "",
					"town_name": "常盤町",
					"building_name": "",
					"organization_name": ""
				}
			},
			"region_code": "関西",
			"prefecture_code": "奈良県",
			"city_code": "橿原市"
		},
		"6340002": {
			"postcode": "634-0002",
			"prefecture_name": "Nara-ken",
			"city_name": "Kashihara-shi",
			"ward_name": "",
			"town_name": "Higashitakedacho",
			"building_name": "",
			"organization_name": "",
			"translations": {
				"ja": {
					"prefecture_name": "奈良県",
					"city_name": "橿原市",
					"ward_name": "",
					"town_name": "東竹田町",
					"building_name": "",
					"organization_name": ""
				}
			},
			"region_code": "関西",
			"prefecture_code": "奈良県",
			"city_code": "橿原市"
		},
		"6340001": {
			"postcode": "634-0001",
			"prefecture_name": "Nara-ken",
			"city_name": "Kashihara-shi",
			"ward_name": "",
			"town_name": "Odaichicho",
			"building_name": "",
			"organization_name": "",
			"translations": {
				"ja": {
					"prefecture_name": "奈良県",
					"city_name": "橿原市",
					"ward_name": "",
					"town_name": "太田市町",
					"building_name": "",
					"organization_name": ""
				}
			},
			"region_code": "関西",
			"prefecture_code": "奈良県",
			"city_code": "橿原市"
		},
		"6340000": {
			"postcode": "634-0000",
			"prefecture_name": "Nara-ken",
			"city_name": "Kashihara-shi",
			"ward_name": "",
			"town_name": "",
			"building_name": "",
			"organization_name": "",
			"translations": {
				"ja": {
					"prefecture_name": "奈良県",
					"city_name": "橿原市",
					"ward_name": "",
					"town_name": "",
					"building_name": "",
					"organization_name": ""
				}
			},
			"region_code": "関西",
			"prefecture_code": "奈良県",
			"city_code": "橿原市"
		}
	}
}