{
	"country_code": "JP",
	"parent_id": "713",
	"locale": "ja-Latn",
	"address": {
		"7138713": {
			"postcode": "713-8713",
			"prefecture_name": "Okayama-ken",
			"city_name": "Kurashiki-shi",
			"ward_name": "",
			"town_name": "玉島阿賀崎",
			"building_name": "１丁目４−１１（玉島郵便局私書箱第５号）",
			"organization_name": "赤澤屋　株式会社",
			"region_code": "中国",
			"prefecture_code": "岡山県",
			"city_code": "倉敷市",
			"translations": {
				"ja": {
					"prefecture_name": "岡山県",
					"city_name": "倉敷市",
					"ward_name": "",
					"town_name": "玉島阿賀崎",
					"building_name": "１丁目４−１１（玉島郵便局私書箱第５号）",
					"organization_name": "赤澤屋　株式会社"
				}
			}
		},
		"7138686": {
			"postcode": "713-8686",
			"prefecture_name": "Okayama-ken",
			"city_name": "Kurashiki-shi",
			"ward_name": "",
			"town_name": "玉島",
			"building_name": "１４３８（玉島郵便局私書箱第７号）",
			"organization_name": "玉島信用金庫",
			"region_code": "中国",
			"prefecture_code": "岡山県",
			"city_code": "倉敷市",
			"translations": {
				"ja": {
					"prefecture_name": "岡山県",
					"city_name": "倉敷市",
					"ward_name": "",
					"town_name": "玉島",
					"building_name": "１４３８（玉島郵便局私書箱第７号）",
					"organization_name": "玉島信用金庫"
				}
			}
		},
		"7138668": {
			"postcode": "713-8668",
			"prefecture_name": "Okayama-ken",
			"city_name": "Kurashiki-shi",
			"ward_name": "",
			"town_name": "玉島阿賀崎",
			"building_name": "３丁目１−１（玉島郵便局私書箱第４号）",
			"organization_name": "岡山県立　玉島高等学校",
			"region_code": "中国",
			"prefecture_code": "岡山県",
			"city_code": "倉敷市",
			"translations": {
				"ja": {
					"prefecture_name": "岡山県",
					"city_name": "倉敷市",
					"ward_name": "",
					"town_name": "玉島阿賀崎",
					"building_name": "３丁目１−１（玉島郵便局私書箱第４号）",
					"organization_name": "岡山県立　玉島高等学校"
				}
			}
		},
		"7138666": {
			"postcode": "713-8666",
			"prefecture_name": "Okayama-ken",
			"city_name": "Kurashiki-shi",
			"ward_name": "",
			"town_name": "玉島勇崎",
			"building_name": "１２９２（玉島郵便局私書箱第６号）",
			"organization_name": "株式会社　鯛惣",
			"region_code": "中国",
			"prefecture_code": "岡山県",
			"city_code": "倉敷市",
			"translations": {
				"ja": {
					"prefecture_name": "岡山県",
					"city_name": "倉敷市",
					"ward_name": "",
					"town_name": "玉島勇崎",
					"building_name": "１２９２（玉島郵便局私書箱第６号）",
					"organization_name": "株式会社　鯛惣"
				}
			}
		},
		"7138601": {
			"postcode": "713-8601",
			"prefecture_name": "Okayama-ken",
			"city_name": "Kurashiki-shi",
			"ward_name": "",
			"town_name": "玉島阿賀崎",
			"building_name": "２丁目１−５０（玉島郵便局私書箱第１４号）",
			"organization_name": "玉島　税務署",
			"region_code": "中国",
			"prefecture_code": "岡山県",
			"city_code": "倉敷市",
			"translations": {
				"ja": {
					"prefecture_name": "岡山県",
					"city_name": "倉敷市",
					"ward_name": "",
					"town_name": "玉島阿賀崎",
					"building_name": "２丁目１−５０（玉島郵便局私書箱第１４号）",
					"organization_name": "玉島　税務署"
				}
			}
		},
		"7138577": {
			"postcode": "713-8577",
			"prefecture_name": "Okayama-ken",
			"city_name": "Kurashiki-shi",
			"ward_name": "",
			"town_name": "玉島柏島",
			"building_name": "７０４７",
			"organization_name": "立花容器　株式会社",
			"region_code": "中国",
			"prefecture_code": "岡山県",
			"city_code": "倉敷市",
			"translations": {
				"ja": {
					"prefecture_name": "岡山県",
					"city_name": "倉敷市",
					"ward_name": "",
					"town_name": "玉島柏島",
					"building_name": "７０４７",
					"organization_name": "立花容器　株式会社"
				}
			}
		},
		"7138565": {
			"postcode": "713-8565",
			"prefecture_name": "Okayama-ken",
			"city_name": "Kurashiki-shi",
			"ward_name": "",
			"town_name": "玉島阿賀崎",
			"building_name": "１丁目１−１",
			"organization_name": "倉敷市　玉島支所",
			"region_code": "中国",
			"prefecture_code": "岡山県",
			"city_code": "倉敷市",
			"translations": {
				"ja": {
					"prefecture_name": "岡山県",
					"city_name": "倉敷市",
					"ward_name": "",
					"town_name": "玉島阿賀崎",
					"building_name": "１丁目１−１",
					"organization_name": "倉敷市　玉島支所"
				}
			}
		},
		"7138550": {
			"postcode": "713-8550",
			"prefecture_name": "Okayama-ken",
			"city_name": "Kurashiki-shi",
			"ward_name": "",
			"town_name": "玉島乙島",
			"building_name": "７４７１",
			"organization_name": "株式会社　クラレ　倉敷事業所　（玉島）",
			"region_code": "中国",
			"prefecture_code": "岡山県",
			"city_code": "倉敷市",
			"translations": {
				"ja": {
					"prefecture_name": "岡山県",
					"city_name": "倉敷市",
					"ward_name": "",
					"town_name": "玉島乙島",
					"building_name": "７４７１",
					"organization_name": "株式会社　クラレ　倉敷事業所　（玉島）"
				}
			}
		},
		"7138501": {
			"postcode": "713-8501",
			"prefecture_name": "Okayama-ken",
			"city_name": "Kurashiki-shi",
			"ward_name": "",
			"town_name": "玉島乙島",
			"building_name": "８２３０",
			"organization_name": "住友重機械工業　株式会社　岡山製造所",
			"region_code": "中国",
			"prefecture_code": "岡山県",
			"city_code": "倉敷市",
			"translations": {
				"ja": {
					"prefecture_name": "岡山県",
					"city_name": "倉敷市",
					"ward_name": "",
					"town_name": "玉島乙島",
					"building_name": "８２３０",
					"organization_name": "住友重機械工業　株式会社　岡山製造所"
				}
			}
		},
		"7138127": {
			"postcode": "713-8127",
			"prefecture_name": "Okayama-ken",
			"city_name": "Kurashiki-shi",
			"ward_name": "",
			"town_name": "Tamashima",
			"building_name": "Kurosakishimmachi",
			"organization_name": "",
			"translations": {
				"ja": {
					"prefecture_name": "岡山県",
					"city_name": "倉敷市",
					"ward_name": "",
					"town_name": "玉島",
					"building_name": "",
					"organization_name": ""
				}
			},
			"region_code": "中国",
			"prefecture_code": "岡山県",
			"city_code": "倉敷市"
		},
		"7138126": {
			"postcode": "713-8126",
			"prefecture_name": "Okayama-ken",
			"city_name": "Kurashiki-shi",
			"ward_name": "",
			"town_name": "Tamashima",
			"building_name": "Kurosaki",
			"organization_name": "",
			"translations": {
				"ja": {
					"prefecture_name": "岡山県",
					"city_name": "倉敷市",
					"ward_name": "",
					"town_name": "玉島",
					"building_name": "",
					"organization_name": ""
				}
			},
			"region_code": "中国",
			"prefecture_code": "岡山県",
			"city_code": "倉敷市"
		},
		"7138125": {
			"postcode": "713-8125",
			"prefecture_name": "Okayama-ken",
			"city_name": "Kurashiki-shi",
			"ward_name": "",
			"town_name": "Tamashima",
			"building_name": "Yuzaki",
			"organization_name": "",
			"translations": {
				"ja": {
					"prefecture_name": "岡山県",
					"city_name": "倉敷市",
					"ward_name": "",
					"town_name": "玉島",
					"building_name": "",
					"organization_name": ""
				}
			},
			"region_code": "中国",
			"prefecture_code": "岡山県",
			"city_code": "倉敷市"
		},
		"7138124": {
			"postcode": "713-8124",
			"prefecture_name": "Okayama-ken",
			"city_name": "Kurashiki-shi",
			"ward_name": "",
			"town_name": "Tamashima",
			"building_name": "Kashiwadai",
			"organization_name": "",
			"translations": {
				"ja": {
					"prefecture_name": "岡山県",
					"city_name": "倉敷市",
					"ward_name": "",
					"town_name": "玉島",
					"building_name": "",
					"organization_name": ""
				}
			},
			"region_code": "中国",
			"prefecture_code": "岡山県",
			"city_code": "倉敷市"
		},
		"7138123": {
			"postcode": "713-8123",
			"prefecture_name": "Okayama-ken",
			"city_name": "Kurashiki-shi",
			"ward_name": "",
			"town_name": "Tamashima",
			"building_name": "Kashiwajima",
			"organization_name": "",
			"translations": {
				"ja": {
					"prefecture_name": "岡山県",
					"city_name": "倉敷市",
					"ward_name": "",
					"town_name": "玉島",
					"building_name": "",
					"organization_name": ""
				}
			},
			"region_code": "中国",
			"prefecture_code": "岡山県",
			"city_code": "倉敷市"
		},
		"7138122": {
			"postcode": "713-8122",
			"prefecture_name": "Okayama-ken",
			"city_name": "Kurashiki-shi",
			"ward_name": "",
			"town_name": "Tamashima",
			"building_name": "Chuocho",
			"organization_name": "",
			"translations": {
				"ja": {
					"prefecture_name": "岡山県",
					"city_name": "倉敷市",
					"ward_name": "",
					"town_name": "玉島",
					"building_name": "",
					"organization_name": ""
				}
			},
			"region_code": "中国",
			"prefecture_code": "岡山県",
			"city_code": "倉敷市"
		},
		"7138121": {
			"postcode": "713-8121",
			"prefecture_name": "Okayama-ken",
			"city_name": "Kurashiki-shi",
			"ward_name": "",
			"town_name": "Tamashima",
			"building_name": "Agasaki",
			"organization_name": "",
			"translations": {
				"ja": {
					"prefecture_name": "岡山県",
					"city_name": "倉敷市",
					"ward_name": "",
					"town_name": "玉島",
					"building_name": "",
					"organization_name": ""
				}
			},
			"region_code": "中国",
			"prefecture_code": "岡山県",
			"city_code": "倉敷市"
		},
		"7138116": {
			"postcode": "713-8116",
			"prefecture_name": "Okayama-ken",
			"city_name": "Kurashiki-shi",
			"ward_name": "",
			"town_name": "Tamashima",
			"building_name": "Tomi",
			"organization_name": "",
			"translations": {
				"ja": {
					"prefecture_name": "岡山県",
					"city_name": "倉敷市",
					"ward_name": "",
					"town_name": "玉島",
					"building_name": "",
					"organization_name": ""
				}
			},
			"region_code": "中国",
			"prefecture_code": "岡山県",
			"city_code": "倉敷市"
		},
		"7138115": {
			"postcode": "713-8115",
			"prefecture_name": "Okayama-ken",
			"city_name": "Kurashiki-shi",
			"ward_name": "",
			"town_name": "Tamashima",
			"building_name": "Michiguchi",
			"organization_name": "",
			"translations": {
				"ja": {
					"prefecture_name": "岡山県",
					"city_name": "倉敷市",
					"ward_name": "",
					"town_name": "玉島",
					"building_name": "",
					"organization_name": ""
				}
			},
			"region_code": "中国",
			"prefecture_code": "岡山県",
			"city_code": "倉敷市"
		},
		"7138114": {
			"postcode": "713-8114",
			"prefecture_name": "Okayama-ken",
			"city_name": "Kurashiki-shi",
			"ward_name": "",
			"town_name": "Tamashima",
			"building_name": "Michigoe",
			"organization_name": "",
			"translations": {
				"ja": {
					"prefecture_name": "岡山県",
					"city_name": "倉敷市",
					"ward_name": "",
					"town_name": "玉島",
					"building_name": "",
					"organization_name": ""
				}
			},
			"region_code": "中国",
			"prefecture_code": "岡山県",
			"city_code": "倉敷市"
		},
		"7138113": {
			"postcode": "713-8113",
			"prefecture_name": "Okayama-ken",
			"city_name": "Kurashiki-shi",
			"ward_name": "",
			"town_name": "Tamashima",
			"building_name": "Yashima",
			"organization_name": "",
			"translations": {
				"ja": {
					"prefecture_name": "岡山県",
					"city_name": "倉敷市",
					"ward_name": "",
					"town_name": "玉島",
					"building_name": "",
					"organization_name": ""
				}
			},
			"region_code": "中国",
			"prefecture_code": "岡山県",
			"city_code": "倉敷市"
		},
		"7138112": {
			"postcode": "713-8112",
			"prefecture_name": "Okayama-ken",
			"city_name": "Kurashiki-shi",
			"ward_name": "",
			"town_name": "Tamashima",
			"building_name": "Sue",
			"organization_name": "",
			"translations": {
				"ja": {
					"prefecture_name": "岡山県",
					"city_name": "倉敷市",
					"ward_name": "",
					"town_name": "玉島",
					"building_name": "",
					"organization_name": ""
				}
			},
			"region_code": "中国",
			"prefecture_code": "岡山県",
			"city_code": "倉敷市"
		},
		"7138111": {
			"postcode": "713-8111",
			"prefecture_name": "Okayama-ken",
			"city_name": "Kurashiki-shi",
			"ward_name": "",
			"town_name": "Tamashima",
			"building_name": "Hattori",
			"organization_name": "",
			"translations": {
				"ja": {
					"prefecture_name": "岡山県",
					"city_name": "倉敷市",
					"ward_name": "",
					"town_name": "玉島",
					"building_name": "",
					"organization_name": ""
				}
			},
			"region_code": "中国",
			"prefecture_code": "岡山県",
			"city_code": "倉敷市"
		},
		"7138103": {
			"postcode": "713-8103",
			"prefecture_name": "Okayama-ken",
			"city_name": "Kurashiki-shi",
			"ward_name": "",
			"town_name": "Tamashima",
			"building_name": "Otoshima",
			"organization_name": "",
			"translations": {
				"ja": {
					"prefecture_name": "岡山県",
					"city_name": "倉敷市",
					"ward_name": "",
					"town_name": "玉島",
					"building_name": "",
					"organization_name": ""
				}
			},
			"region_code": "中国",
			"prefecture_code": "岡山県",
			"city_code": "倉敷市"
		},
		"7138102": {
			"postcode": "713-8102",
			"prefecture_name": "Okayama-ken",
			"city_name": "Kurashiki-shi",
			"ward_name": "",
			"town_name": "Tamashima",
			"building_name": "",
			"organization_name": "",
			"translations": {
				"ja": {
					"prefecture_name": "岡山県",
					"city_name": "倉敷市",
					"ward_name": "",
					"town_name": "玉島",
					"building_name": "",
					"organization_name": ""
				}
			},
			"region_code": "中国",
			"prefecture_code": "岡山県",
			"city_code": "倉敷市"
		},
		"7138101": {
			"postcode": "713-8101",
			"prefecture_name": "Okayama-ken",
			"city_name": "Kurashiki-shi",
			"ward_name": "",
			"town_name": "Tamashima",
			"building_name": "Uwanari",
			"organization_name": "",
			"translations": {
				"ja": {
					"prefecture_name": "岡山県",
					"city_name": "倉敷市",
					"ward_name": "",
					"town_name": "玉島",
					"building_name": "",
					"organization_name": ""
				}
			},
			"region_code": "中国",
			"prefecture_code": "岡山県",
			"city_code": "倉敷市"
		}
	}
}